matrix_pomdp/__init__.py
matrix_pomdp/envs/__init__.py
matrix_pomdp/envs/matrix_pomdp.py
matrix_pomdp_gym-0.1.0.dist-info/licenses/LICENSE
matrix_pomdp_gym-0.1.0.dist-info/METADATA
matrix_pomdp_gym-0.1.0.dist-info/WHEEL
matrix_pomdp_gym-0.1.0.dist-info/top_level.txt
matrix_pomdp_gym-0.1.0.dist-info/RECORD
