Metadata-Version: 2.4
Name: matrix-pomdp-gym
Version: 0.1.0
Summary: An OpenAI gym / Gymnasium environment for discrete-action, continuous-observation Partially Observable Markov Decision Processes (POMDPs) using matrices.
Home-page: https://github.com/asmteran/matrix-pomdp-gym
Author: A. Saleh Mteran
Author-email: a.salehmteran@gmail.com
License: MIT License
Keywords: Reinforcement-Learning Reinforcement-Learning-Environment Gym-Environment Markov-Decision-Processes Gym OpenAI-Gym Gymnasium
Classifier: Programming Language :: Python :: 3
Classifier: Programming Language :: Python :: 3 :: Only
Classifier: Programming Language :: Python :: 3.7
Classifier: Programming Language :: Python :: 3.8
Classifier: Programming Language :: Python :: 3.9
Classifier: License :: OSI Approved :: MIT License
Classifier: Operating System :: OS Independent
Classifier: Intended Audience :: Developers
Classifier: Intended Audience :: Education
Classifier: Intended Audience :: Science/Research
Classifier: Topic :: Scientific/Engineering
Classifier: Topic :: Scientific/Engineering :: Mathematics
Classifier: Topic :: Scientific/Engineering :: Artificial Intelligence
Classifier: Topic :: Software Development
Classifier: Topic :: Software Development :: Libraries
Classifier: Topic :: Software Development :: Libraries :: Python Modules
Requires-Python: >=3.6
License-File: LICENSE
Requires-Dist: gymnasium>=0.26.2
Requires-Dist: numpy>=1.26.4
Dynamic: author
Dynamic: author-email
Dynamic: classifier
Dynamic: description
Dynamic: description-content-type
Dynamic: home-page
Dynamic: keywords
Dynamic: license
Dynamic: license-file
Dynamic: requires-dist
Dynamic: requires-python
Dynamic: summary
